CHANGELOG.md
MANIFEST.in
README.md
setup.cfg
setup.py
tailbone_nationbuilder/__init__.py
tailbone_nationbuilder/_version.py
tailbone_nationbuilder/menus.py
tailbone_nationbuilder/provider.py
tailbone_nationbuilder.egg-info/PKG-INFO
tailbone_nationbuilder.egg-info/SOURCES.txt
tailbone_nationbuilder.egg-info/dependency_links.txt
tailbone_nationbuilder.egg-info/entry_points.txt
tailbone_nationbuilder.egg-info/requires.txt
tailbone_nationbuilder.egg-info/top_level.txt
tailbone_nationbuilder/views/__init__.py
tailbone_nationbuilder/views/nationbuilder/__init__.py
tailbone_nationbuilder/views/nationbuilder/donations.py
tailbone_nationbuilder/views/nationbuilder/master.py
tailbone_nationbuilder/views/nationbuilder/people.py